<annotation>
	<folder></folder>
	<filename>a2_110_jpg.rf.9bec8011f366213498911ce6f69459e5.jpg</filename>
	<path>a2_110_jpg.rf.9bec8011f366213498911ce6f69459e5.jpg</path>
	<source>
		<database>roboflow.com</database>
	</source>
	<size>
		<width>640</width>
		<height>640</height>
		<depth>3</depth>
	</size>
	<segmented>0</segmented>
	<object>
		<name>stair</name>
		<pose>Unspecified</pose>
		<truncated>0</truncated>
		<difficult>0</difficult>
		<occluded>0</occluded>
		<bndbox>
			<xmin>1</xmin>
			<xmax>641</xmax>
			<ymin>48</ymin>
			<ymax>641</ymax>
		</bndbox>
	</object>
</annotation>
